sso/__init__.py
sso/exceptions.py
sso/json_schema.json
sso/services.json
sso/sso.py
sso/version.py
pod_sso-1.0.2.dist-info/LICENSE
pod_sso-1.0.2.dist-info/METADATA
pod_sso-1.0.2.dist-info/WHEEL
pod_sso-1.0.2.dist-info/top_level.txt
pod_sso-1.0.2.dist-info/RECORD
