Metadata-Version: 2.1
Name: pod-sso
Version: 1.0.2
Summary: This package for implementation of POD platform SSO APIs
Home-page: https://github.com/FanapSoft/pod-sso-python-sdk
Author: ReZa ZaRe
Author-email: rz.zare@gmail.com
License: MIT
Project-URL: Source, https://github.com/FanapSoft/pod-sso-python-sdk
Project-URL: Documentation, http://docs.pod.ir/v1.0.0.2/PODSDKs/python/5233/user
Project-URL: Tracker, https://github.com/FanapSoft/pod-sso-python-sdk/issues
Keywords: pod,single sign on,sso,pod sdk
Platform: UNKNOWN
Classifier: Natural Language :: Persian
Classifier: Natural Language :: English
Classifier: Programming Language :: Python
Classifier: Programming Language :: Python :: 2
Classifier: Programming Language :: Python :: 2.7
Classifier: Programming Language :: Python :: 3
Classifier: Programming Language :: Python :: 3.5
Classifier: Programming Language :: Python :: 3.6
Classifier: Programming Language :: Python :: 3.7
Requires-Python: >=2.7
Requires-Dist: pod-base (<2,>=1.0.3)
Requires-Dist: pycrypto (>=2.6.1)
